{
  "matchDate": "2025-11-09",
  "matchUrl": "https://www.bbc.com/sport/football/live/cx2pggrjk8et#Line-ups",
  "competition": "Premier League",
  "stadiumName": "Selhurst Park",
  "score": "0 - 0",
  "homeTeam": {
    "name": "Crystal Palace",
    "code": "crystal-palace",
    "formation": "3-4-2-1",
    "players": [
      {
        "number": 1,
        "name": "Henderson",
        "originalPosition": "Goalkeeper",
        "position": "GK"
      },
      {
        "number": 26,
        "name": "Richards",
        "originalPosition": "Defender",
        "position": "RCB"
      },
      {
        "number": 5,
        "name": "Lacroix",
        "originalPosition": "Defender",
        "position": "CB"
      },
      {
        "number": 23,
        "name": "Canvot",
        "originalPosition": "Defender",
        "position": "LCB"
      },
      {
        "number": 2,
        "name": "Muñoz",
        "originalPosition": "Midfielder",
        "position": "RM"
      },
      {
        "number": 20,
        "name": "Wharton",
        "originalPosition": "Midfielder",
        "position": "RCM"
      },
      {
        "number": 8,
        "name": "Lerma",
        "originalPosition": "Midfielder",
        "position": "LCM"
      },
      {
        "number": 3,
        "name": "Mitchell",
        "originalPosition": "Midfielder",
        "position": "LM"
      },
      {
        "number": 7,
        "name": "Sarr",
        "originalPosition": "Attacking Midfielder",
        "position": "RAM"
      },
      {
        "number": 18,
        "name": "Kamada",
        "originalPosition": "Attacking Midfielder",
        "position": "LAM"
      },
      {
        "number": 14,
        "name": "Mateta",
        "originalPosition": "Striker",
        "position": "ST"
      }
    ]
  },
  "awayTeam": {
    "name": "Brighton And Hove Albion",
    "code": "brighton-and-hove-albion",
    "formation": "4-2-3-1",
    "players": [
      {
        "number": 1,
        "name": "Verbruggen",
        "originalPosition": "Goalkeeper",
        "position": "GK"
      },
      {
        "number": 27,
        "name": "Wieffer",
        "originalPosition": "Defender",
        "position": "RB"
      },
      {
        "number": 6,
        "name": "van Hecke",
        "originalPosition": "Defender",
        "position": "RCB"
      },
      {
        "number": 5,
        "name": "Dunk",
        "originalPosition": "Defender",
        "position": "LCB"
      },
      {
        "number": 24,
        "name": "Kadioglu",
        "originalPosition": "Defender",
        "position": "LB"
      },
      {
        "number": 17,
        "name": "Baleba",
        "originalPosition": "Defensive Midfielder",
        "position": "RDM"
      },
      {
        "number": 26,
        "name": "Ayari",
        "originalPosition": "Defensive Midfielder",
        "position": "LDM"
      },
      {
        "number": 11,
        "name": "Minteh",
        "originalPosition": "Attacking Midfielder",
        "position": "RAM"
      },
      {
        "number": 10,
        "name": "Rutter",
        "originalPosition": "Attacking Midfielder",
        "position": "CAM"
      },
      {
        "number": 25,
        "name": "Gómez",
        "originalPosition": "Attacking Midfielder",
        "position": "LAM"
      },
      {
        "number": 18,
        "name": "Welbeck",
        "originalPosition": "Striker",
        "position": "ST"
      }
    ]
  }
}