{
  "matchDate": "2025-11-30",
  "matchUrl": "https://www.bbc.com/sport/football/live/cn98xwggveyt#Line-ups",
  "competition": "Premier League",
  "stadiumName": "The City Ground",
  "score": "0 - 2",
  "homeTeam": {
    "name": "Nottingham Forest",
    "code": "nottingham-forest",
    "formation": "4-2-3-1",
    "players": [
      {
        "number": 26,
        "name": "Sels",
        "originalPosition": "Goalkeeper",
        "position": "GK"
      },
      {
        "number": 37,
        "name": "Savona",
        "originalPosition": "Defender",
        "position": "RB"
      },
      {
        "number": 31,
        "name": "Milenkovic",
        "originalPosition": "Defender",
        "position": "RCB"
      },
      {
        "number": 4,
        "name": "Morato",
        "originalPosition": "Defender",
        "position": "LCB"
      },
      {
        "number": 3,
        "name": "Williams",
        "originalPosition": "Defender",
        "position": "LB"
      },
      {
        "number": 6,
        "name": "Sangaré",
        "originalPosition": "Defensive Midfielder",
        "position": "RDM"
      },
      {
        "number": 8,
        "name": "Anderson",
        "originalPosition": "Defensive Midfielder",
        "position": "LDM"
      },
      {
        "number": 14,
        "name": "Ndoye",
        "originalPosition": "Attacking Midfielder",
        "position": "RAM"
      },
      {
        "number": 10,
        "name": "Gibbs-White",
        "originalPosition": "Attacking Midfielder",
        "position": "CAM"
      },
      {
        "number": 16,
        "name": "Domínguez",
        "originalPosition": "Attacking Midfielder",
        "position": "LAM"
      },
      {
        "number": 19,
        "name": "Igor Jesus",
        "originalPosition": "Striker",
        "position": "ST"
      }
    ]
  },
  "awayTeam": {
    "name": "Brighton And Hove Albion",
    "code": "brighton-and-hove-albion",
    "formation": "4-2-3-1",
    "players": [
      {
        "number": 1,
        "name": "Verbruggen",
        "originalPosition": "Goalkeeper",
        "position": "GK"
      },
      {
        "number": 27,
        "name": "Wieffer",
        "originalPosition": "Defender",
        "position": "RB"
      },
      {
        "number": 6,
        "name": "van Hecke",
        "originalPosition": "Defender",
        "position": "RCB"
      },
      {
        "number": 5,
        "name": "Dunk",
        "originalPosition": "Defender",
        "position": "LCB"
      },
      {
        "number": 24,
        "name": "Kadioglu",
        "originalPosition": "Defender",
        "position": "LB"
      },
      {
        "number": 26,
        "name": "Ayari",
        "originalPosition": "Defensive Midfielder",
        "position": "RDM"
      },
      {
        "number": 25,
        "name": "Gómez",
        "originalPosition": "Defensive Midfielder",
        "position": "LDM"
      },
      {
        "number": 11,
        "name": "Minteh",
        "originalPosition": "Attacking Midfielder",
        "position": "RAM"
      },
      {
        "number": 10,
        "name": "Rutter",
        "originalPosition": "Attacking Midfielder",
        "position": "CAM"
      },
      {
        "number": 29,
        "name": "De Cuyper",
        "originalPosition": "Attacking Midfielder",
        "position": "LAM"
      },
      {
        "number": 18,
        "name": "Welbeck",
        "originalPosition": "Striker",
        "position": "ST"
      }
    ]
  }
}